Metadata-Version: 2.1
Name: pinnstf2
Version: 0.1.2
Summary: An implementation of PINNs in TensorFlow v2.
Home-page: https://github.com/rezaakb/pinns-tf2
Author: Reza Akbarian Bafghi
Author-email: reza.akbarianbafghi@coloardo.edu
License: BSD-3-Clause
Classifier: Development Status :: 2 - Pre-Alpha
Classifier: Programming Language :: Python :: 3.9
Classifier: Programming Language :: Python :: 3.10
License-File: LICENSE
